asyncba/__init__.py
asyncba/__version__.py
asyncba-0.0.0.dev0.dist-info/METADATA
asyncba-0.0.0.dev0.dist-info/RECORD
asyncba-0.0.0.dev0.dist-info/WHEEL
asyncba-0.0.0.dev0.dist-info/top_level.txt
